pymining/__init__.py
pymining/assocrules.py
pymining/compat.py
pymining/itemmining.py
pymining/perftesting.py
pymining/seqmining.py
pymining-0.2.dist-info/DESCRIPTION.rst
pymining-0.2.dist-info/METADATA
pymining-0.2.dist-info/metadata.json
pymining-0.2.dist-info/RECORD
pymining-0.2.dist-info/top_level.txt
pymining-0.2.dist-info/WHEEL
